imagegrains/__init__.py
imagegrains/__main__.py
imagegrains/data_loader.py
imagegrains/grainsizing.py
imagegrains/gsd_uncertainty.py
imagegrains/plotting.py
imagegrains/segmentation_helper.py
imagegrains-1.2.1.dist-info/METADATA
imagegrains-1.2.1.dist-info/WHEEL
imagegrains-1.2.1.dist-info/licenses/LICENSE.md
imagegrains-1.2.1.dist-info/RECORD
