Metadata-Version: 2.4
Name: imagegrains
Version: 1.2.1
Summary: A software library for segmenting and measuring of sedimentary particles in images
Project-URL: homepage, https://github.com/dmair1989/imagegrains
Project-URL: repository, https://github.com/dmair1989/imagegrains
Author-email: "David Mair, Guillaume Witz" <david.mair@unibe.ch>
License: BSD 3-Clause License
License-File: LICENSE.md
Requires-Python: >=3.9
Requires-Dist: cellpose==2.3.2
Requires-Dist: imagecodecs
Requires-Dist: jupyterlab>=4.0.0
Requires-Dist: leidenalg
Requires-Dist: matplotlib>=3.7.1
Requires-Dist: numpy<=2.2
Requires-Dist: opentsne
Requires-Dist: pandas>=2.0.0
Requires-Dist: scanpy>=1.9.0
Requires-Dist: scikit-image>=0.20.0
Provides-Extra: test
Requires-Dist: pytest>=6.0; extra == 'test'
